Metadata-Version: 1.1
Name: simple-text-parser
Version: 0.24.2
Summary: Text parser
Home-page: https://github.com/eerimoq/textparser
Author: Eidan Shmidt
Author-email: theeidanshmidt@gmail.com
License: MIT
Keywords: text parser
Platform: UNKNOWN
Classifier: Development Status :: 5 - Production/Stable
Classifier: Intended Audience :: Education
Classifier: Operating System :: OS Independent
Classifier: License :: OSI Approved :: MIT License
Classifier: Programming Language :: Python :: 3
